flask_discord_interactions/__init__.py
flask_discord_interactions/client.py
flask_discord_interactions/command.py
flask_discord_interactions/context.py
flask_discord_interactions/discord.py
flask_discord_interactions/utils.py
flask_discord_interactions/enums/__init__.py
flask_discord_interactions/enums/response_types.py
flask_discord_interactions/models/__init__.py
flask_discord_interactions/models/attachment.py
flask_discord_interactions/models/autocomplete.py
flask_discord_interactions/models/channel.py
flask_discord_interactions/models/command.py
flask_discord_interactions/models/component.py
flask_discord_interactions/models/embed.py
flask_discord_interactions/models/message.py
flask_discord_interactions/models/modal.py
flask_discord_interactions/models/option.py
flask_discord_interactions/models/permission.py
flask_discord_interactions/models/role.py
flask_discord_interactions/models/user.py
flask_discord_interactions/models/utils.py
flask_discord_interactions/tests/__init__.py
flask_discord_interactions/tests/conftest.py
flask_discord_interactions/tests/test_command.py
flask_discord_interactions/tests/test_component.py
flask_discord_interactions/tests/test_context.py
flask_discord_interactions/tests/test_flask.py
flask_discord_interactions/tests/test_full_quart.py
flask_discord_interactions/tests/test_handler.py
flask_discord_interactions/tests/test_options.py
flask_discord_interactions/tests/test_ping.py
flask_discord_interactions/tests/test_quart.py
flask_discord_interactions/tests/test_register.py
flask_discord_interactions/tests/test_response.py
flask_discord_interactions/tests/test_subcommand.py
Flask_Discord_Interactions-2.1.2.dist-info/LICENSE
Flask_Discord_Interactions-2.1.2.dist-info/METADATA
Flask_Discord_Interactions-2.1.2.dist-info/WHEEL
Flask_Discord_Interactions-2.1.2.dist-info/top_level.txt
Flask_Discord_Interactions-2.1.2.dist-info/RECORD
