Metadata-Version: 2.1
Name: Flask-Discord-Interactions
Version: 2.1.2
Summary: A Flask extension for Discord slash commands.
Home-page: https://github.com/breqdev/flask-discord-interactions
Author: Brooke Chalmers
Author-email: breq@breq.dev
Platform: any
Classifier: Environment :: Web Environment
Classifier: Intended Audience :: Developers
Classifier: Operating System :: OS Independent
Classifier: License :: OSI Approved :: MIT License
Classifier: Programming Language :: Python
Requires-Python: >=3.7
Provides-Extra: async
License-File: LICENSE
